modulebooks/__init__.py
modulebooks/example.py
modulebooks-0.0.1.dist-info/licenses/LICENSE
modulebooks-0.0.1.dist-info/METADATA
modulebooks-0.0.1.dist-info/WHEEL
modulebooks-0.0.1.dist-info/top_level.txt
modulebooks-0.0.1.dist-info/RECORD
